Poort-0.3.4.dist-info/DESCRIPTION.rst
Poort-0.3.4.dist-info/METADATA
Poort-0.3.4.dist-info/RECORD
Poort-0.3.4.dist-info/WHEEL
Poort-0.3.4.dist-info/entry_points.txt
Poort-0.3.4.dist-info/metadata.json
Poort-0.3.4.dist-info/top_level.txt
poort/__init__.py
poort/cli.py
poort/gate.py
poort/request.py
poort/response.py
poort/utils.py
