Metadata-Version: 2.0
Name: Poort
Version: 0.3.4
Summary: Poort: The quick gateway.
Home-page: https://github.com/corverdevelopment/Poort/
Author: Nils Corver
Author-email: nils@corverdevelopment.nl
License: MIT
Keywords: about,this,package
Platform: UNKNOWN
Classifier: Development Status :: 3 - Alpha
Classifier: Intended Audience :: Developers
Classifier: Natural Language :: English
Classifier: License :: OSI Approved :: MIT License
Classifier: Operating System :: OS Independent
Classifier: Programming Language :: Python
Classifier: Programming Language :: Python :: 2
Classifier: Programming Language :: Python :: 2.7
Classifier: Programming Language :: Python :: 3
Classifier: Programming Language :: Python :: 3.5
Classifier: Programming Language :: Python :: Implementation :: CPython
Classifier: Topic :: Software Development :: Libraries :: Python Modules
Requires-Dist: Disinfect (>=0.2.1)
Requires-Dist: Jinja2 (>=2.8)
Requires-Dist: Pandora (>=0.2.3)
Requires-Dist: Werkzeug (>=0.11.4)
Requires-Dist: click (>=6.3)
Requires-Dist: gunicorn (>=19.4.5)
Requires-Dist: psutil (>=4.2.0)
Requires-Dist: requests (>=2.9.1)
